setup.py
salure_helpers/datev/__init__.py
salure_helpers/datev/datev.py
salure_helpers/datev/datev_lodas.py
salure_helpers/datev/datev_lodas_mapping.py
salure_helpers/datev/datev_mapping.py
salure_helpers_datev.egg-info/PKG-INFO
salure_helpers_datev.egg-info/SOURCES.txt
salure_helpers_datev.egg-info/dependency_links.txt
salure_helpers_datev.egg-info/not-zip-safe
salure_helpers_datev.egg-info/requires.txt
salure_helpers_datev.egg-info/top_level.txt