Metadata-Version: 1.0
Name: salure-helpers-datev
Version: 1.0.6
Summary: Datev wrapper from Salure
Home-page: UNKNOWN
Author: D&A Salure
Author-email: support@salureconnnect.com
License: Salure License
Platform: UNKNOWN
